README.md
setup.cfg
setup.py
xdeepctr/__init__.py
xdeepctr/feature_column.py
xdeepctr/inputs.py
xdeepctr/utils.py
xdeepctr.egg-info/PKG-INFO
xdeepctr.egg-info/SOURCES.txt
xdeepctr.egg-info/dependency_links.txt
xdeepctr.egg-info/requires.txt
xdeepctr.egg-info/top_level.txt
xdeepctr/contrib/__init__.py
xdeepctr/contrib/rnn.py
xdeepctr/contrib/rnn_v2.py
xdeepctr/contrib/utils.py
xdeepctr/estimator/__init__.py
xdeepctr/estimator/feature_column.py
xdeepctr/estimator/inputs.py
xdeepctr/estimator/utils.py
xdeepctr/estimator/models/__init__.py
xdeepctr/estimator/models/afm.py
xdeepctr/estimator/models/autoint.py
xdeepctr/estimator/models/ccpm.py
xdeepctr/estimator/models/dcn.py
xdeepctr/estimator/models/deepfefm.py
xdeepctr/estimator/models/deepfm.py
xdeepctr/estimator/models/fibinet.py
xdeepctr/estimator/models/fnn.py
xdeepctr/estimator/models/fwfm.py
xdeepctr/estimator/models/nfm.py
xdeepctr/estimator/models/pnn.py
xdeepctr/estimator/models/wdl.py
xdeepctr/estimator/models/xdeepfm.py
xdeepctr/layers/__init__.py
xdeepctr/layers/activation.py
xdeepctr/layers/core.py
xdeepctr/layers/interaction.py
xdeepctr/layers/normalization.py
xdeepctr/layers/sequence.py
xdeepctr/layers/utils.py
xdeepctr/models/__init__.py
xdeepctr/models/afm.py
xdeepctr/models/autoint.py
xdeepctr/models/ccpm.py
xdeepctr/models/dcn.py
xdeepctr/models/dcnmix.py
xdeepctr/models/deepfefm.py
xdeepctr/models/deepfm.py
xdeepctr/models/difm.py
xdeepctr/models/fgcnn.py
xdeepctr/models/fibinet.py
xdeepctr/models/flen.py
xdeepctr/models/fnn.py
xdeepctr/models/fwfm.py
xdeepctr/models/ifm.py
xdeepctr/models/mlr.py
xdeepctr/models/nfm.py
xdeepctr/models/onn.py
xdeepctr/models/pnn.py
xdeepctr/models/wdl.py
xdeepctr/models/xdeepfm.py
xdeepctr/models/multitask/__init__.py
xdeepctr/models/multitask/esmm.py
xdeepctr/models/multitask/mmoe.py
xdeepctr/models/multitask/ple.py
xdeepctr/models/multitask/sharedbottom.py
xdeepctr/models/sequence/__init__.py
xdeepctr/models/sequence/bst.py
xdeepctr/models/sequence/dien.py
xdeepctr/models/sequence/din.py
xdeepctr/models/sequence/dsin.py