Metadata-Version: 2.1
Name: xdeepctr
Version: 0.0.0
Summary: Extended version of deepctr
Home-page: https://github.com/shenweichen/deepctr
Author: Weichen Shen
Author-email: weichenswc@163.com
License: Apache-2.0
Download-URL: https://github.com/shenweichen/deepctr/tags
Keywords: ctr,click through rate,deep learning,tensorflow,tensor,keras
Platform: UNKNOWN
Classifier: License :: OSI Approved :: Apache Software License
Classifier: Operating System :: OS Independent
Classifier: Intended Audience :: Developers
Classifier: Intended Audience :: Education
Classifier: Intended Audience :: Science/Research
Classifier: Programming Language :: Python :: 3
Classifier: Programming Language :: Python :: 2.7
Classifier: Programming Language :: Python :: 3.5
Classifier: Programming Language :: Python :: 3.6
Classifier: Programming Language :: Python :: 3.7
Classifier: Programming Language :: Python :: 3.8
Classifier: Topic :: Scientific/Engineering
Classifier: Topic :: Scientific/Engineering :: Artificial Intelligence
Classifier: Topic :: Software Development
Classifier: Topic :: Software Development :: Libraries
Classifier: Topic :: Software Development :: Libraries :: Python Modules
Requires-Python: >=2.7,!=3.0.*,!=3.1.*,!=3.2.*,!=3.3.*,!=3.4.*
Provides-Extra: cpu
Provides-Extra: gpu
